qdrant_openapi/__init__.py
qdrant_openapi/api_client.py
qdrant_openapi/configuration.py
qdrant_openapi/exceptions.py
qdrant_openapi/model_utils.py
qdrant_openapi/rest.py
qdrant_openapi/api/__init__.py
qdrant_openapi/api/cluster_api.py
qdrant_openapi/api/collections_api.py
qdrant_openapi/api/points_api.py
qdrant_openapi/api/service_api.py
qdrant_openapi/api/snapshots_api.py
qdrant_openapi/apis/__init__.py
qdrant_openapi/model/__init__.py
qdrant_openapi/model/abort_transfer_operation.py
qdrant_openapi/model/alias_description.py
qdrant_openapi/model/alias_operations.py
qdrant_openapi/model/any_variants.py
qdrant_openapi/model/app_build_telemetry.py
qdrant_openapi/model/app_features_telemetry.py
qdrant_openapi/model/batch.py
qdrant_openapi/model/batch_vector_struct.py
qdrant_openapi/model/binary_quantization.py
qdrant_openapi/model/binary_quantization_config.py
qdrant_openapi/model/change_aliases_operation.py
qdrant_openapi/model/clear_payload_operation.py
qdrant_openapi/model/cluster_config_telemetry.py
qdrant_openapi/model/cluster_operations.py
qdrant_openapi/model/cluster_status.py
qdrant_openapi/model/cluster_status_one_of.py
qdrant_openapi/model/cluster_status_one_of1.py
qdrant_openapi/model/cluster_status_telemetry.py
qdrant_openapi/model/cluster_telemetry.py
qdrant_openapi/model/collection_cluster_info.py
qdrant_openapi/model/collection_config.py
qdrant_openapi/model/collection_description.py
qdrant_openapi/model/collection_info.py
qdrant_openapi/model/collection_params.py
qdrant_openapi/model/collection_params_diff.py
qdrant_openapi/model/collection_status.py
qdrant_openapi/model/collection_telemetry.py
qdrant_openapi/model/collection_telemetry_enum.py
qdrant_openapi/model/collections_aggregated_telemetry.py
qdrant_openapi/model/collections_aliases_response.py
qdrant_openapi/model/collections_response.py
qdrant_openapi/model/collections_telemetry.py
qdrant_openapi/model/compression_ratio.py
qdrant_openapi/model/condition.py
qdrant_openapi-1.0.1.dist-info/METADATA
qdrant_openapi-1.0.1.dist-info/WHEEL
qdrant_openapi-1.0.1.dist-info/top_level.txt
qdrant_openapi-1.0.1.dist-info/RECORD
