Metadata-Version: 2.1
Name: qdrant-openapi
Version: 1.0.1
Summary: Qdrant API
Home-page: 
Author: OpenAPI Generator community
Author-email: andrey@vasnetsov.com
License: Apache 2.0
Keywords: OpenAPI,OpenAPI-Generator,Qdrant API
Requires-Python: >=3.6
Requires-Dist: urllib3 >=1.25.3
Requires-Dist: python-dateutil
